encrypt_backup.py
encrypt_backup-0.0.14.dist-info/METADATA
encrypt_backup-0.0.14.dist-info/WHEEL
encrypt_backup-0.0.14.dist-info/licenses/LICENSE
encrypt_backup-0.0.14.dist-info/RECORD
