Metadata-Version: 2.3
Name: encrypt-backup
Version: 0.0.14
Summary: A small program for encrypting and decrypting backup files, and generating RSA keys
Author-email: MouseRider <pyu@bapi.eu.org>
License-File: LICENSE
Classifier: License :: OSI Approved :: MIT License
Classifier: Operating System :: OS Independent
Classifier: Programming Language :: Python :: 3
Requires-Python: >=3.8
Requires-Dist: cryptography
Requires-Dist: curl-cffi
